getUserName/__init__.py
getUserName/getUname.py
getUserName-0.1.dist-info/DESCRIPTION.rst
getUserName-0.1.dist-info/METADATA
getUserName-0.1.dist-info/RECORD
getUserName-0.1.dist-info/WHEEL
getUserName-0.1.dist-info/metadata.json
getUserName-0.1.dist-info/top_level.txt
