Metadata-Version: 2.0
Name: getUserName
Version: 0.1
Summary: Gets system Username
Home-page: UNKNOWN
Author: karthik
Author-email: patkarkarthik@gmail.com
License: kar
Platform: UNKNOWN
